openmpdl/DL_PRACTICAL/1_boston-housing-neural-network.ipynb
openmpdl/DL_PRACTICAL/2_new_sentiment-classification-using-cnn-lstm.ipynb
openmpdl/DL_PRACTICAL/2_old_imdb-review-sentimental-analysis-with-keras.ipynb
openmpdl/DL_PRACTICAL/3_fashion-mnist-classification.ipynb
openmpdl/DL_PRACTICAL/4_Stock_price_prediction_LSTM.ipynb
openmpdl/DL_PRACTICAL/Google_Stock_Price_Test.csv
openmpdl/DL_PRACTICAL/Google_Stock_Price_Train.csv
openmpdl/DL_PRACTICAL/HousingData.csv
openmpdl/HPC_Practical/1_BFS and DFS parallel using tree.docx
openmpdl/HPC_Practical/1_BFS_GRAPH.cpp
openmpdl/HPC_Practical/1_BFS_TREE.cpp
openmpdl/HPC_Practical/1_DFS_GRAPH.cpp
openmpdl/HPC_Practical/1_DFS_TREE.cpp
openmpdl/HPC_Practical/2_bubble and merge sort parallel.docx
openmpdl/HPC_Practical/2_bubble_sort_parallel.cpp
openmpdl/HPC_Practical/2_bubble_sort_sequential.cpp
openmpdl/HPC_Practical/2_merge_sort_parallel.cpp
openmpdl/HPC_Practical/2_merge_sort_sequential.cpp
openmpdl/HPC_Practical/3_Parallel Reduction using OpenMP.docx
openmpdl/HPC_Practical/3_parallel_reduction_openmp.cpp
openmpdl/HPC_Practical/3_parallel_reduction_without_openmp.cpp
openmpdl/HPC_Practical/4_cuda pgms.py
openmpdl/HPC_Practical/Mpih Installation.docx
openmpdl/HPC_Practical/OpenMp Code Running Commands.docx
openmpdl/HPC_Practical/Practical_4.ipynb
openmpdl/HPC_Practical/cuda_google_colab_running .docx
openmpdl/HPC_Practical/demo.txt
openmpdl-1.1.1.dist-info/LICENSE
openmpdl-1.1.1.dist-info/METADATA
openmpdl-1.1.1.dist-info/WHEEL
openmpdl-1.1.1.dist-info/top_level.txt
openmpdl-1.1.1.dist-info/RECORD
