Metadata-Version: 2.1
Name: openmpdl
Version: 1.1.1
Summary: short package description demo version3
Author: ORION_B
Author-email: obanarse@gmail.com
Classifier: Programming Language :: Python :: 3
Classifier: License :: OSI Approved :: MIT License
Classifier: Operating System :: OS Independent
Requires-Python: >=3.6
License-File: LICENSE
